{
  "EXPLODINGKITTEN_1": {
    "title": "card.explodingKitten.title",
    "subtitle": "global.empty",
    "description": "card.explodingKitten.description",
    "imageUrl": "exploding_kitten_1.png"
  },
  "EXPLODINGKITTEN_2": {
    "title": "card.explodingKitten.title",
    "subtitle": "global.empty",
    "description": "card.explodingKitten.description",
    "imageUrl": "exploding_kitten_2.png"
  },
  "EXPLODINGKITTEN_3": {
    "title": "card.explodingKitten.title",
    "subtitle": "global.empty",
    "description": "card.explodingKitten.description",
    "imageUrl": "exploding_kitten_3.png"
  },
  "DEFUSE_1": {
    "title": "card.defuse.title",
    "subtitle": "card.defuse.subtitle1",
    "description": "card.defuse.description",
    "imageUrl": "defuse_1.png"
  },
  "DEFUSE_2": {
    "title": "card.defuse.title",
    "subtitle": "card.defuse.subtitle2",
    "description": "card.defuse.description",
    "imageUrl": "defuse_2.png"
  },
  "DEFUSE_3": {
    "title": "card.defuse.title",
    "subtitle": "card.defuse.subtitle3",
    "description": "card.defuse.description",
    "imageUrl": "defuse_3.png"
  },
  "DEFUSE_4": {
    "title": "card.defuse.title",
    "subtitle": "card.defuse.subtitle4",
    "description": "card.defuse.description",
    "imageUrl": "defuse_4.png"
  },
  "DEFUSE_5": {
    "title": "card.defuse.title",
    "subtitle": "card.defuse.subtitle5",
    "description": "card.defuse.description",
    "imageUrl": "defuse_5.png"
  },
  "ATTACK_1": {
    "title": "card.attack.title",
    "subtitle": "card.attack.subtitle1",
    "description": "card.attack.description",
    "imageUrl": "attack_1.png"
  },
  "ATTACK_2": {
    "title": "card.attack.title",
    "subtitle": "card.attack.subtitle2",
    "description": "card.attack.description",
    "imageUrl": "attack_2.png"
  },
  "ATTACK_3": {
    "title": "card.attack.title",
    "subtitle": "card.attack.subtitle3",
    "description": "card.attack.description",
    "imageUrl": "attack_3.png"
  },
  "SHUFFLE_1": {
    "title": "card.shuffle.title",
    "subtitle": "card.shuffle.subtitle1",
    "description": "card.shuffle.description",
    "imageUrl": "shuffle_1.png"
  },
  "SHUFFLE_2": {
    "title": "card.shuffle.title",
    "subtitle": "card.shuffle.subtitle2",
    "description": "card.shuffle.description",
    "imageUrl": "shuffle_2.png"
  },
  "SHUFFLE_3": {
    "title": "card.shuffle.title",
    "subtitle": "card.shuffle.subtitle3",
    "description": "card.shuffle.description",
    "imageUrl": "shuffle_3.png"
  },
  "SHUFFLE_4": {
    "title": "card.shuffle.title",
    "subtitle": "card.shuffle.subtitle4",
    "description": "card.shuffle.description",
    "imageUrl": "shuffle_4.png"
  },
  "SKIP_1": {
    "title": "card.skip.title",
    "subtitle": "card.skip.subtitle1",
    "description": "card.skip.description",
    "imageUrl": "skip_1.png"
  },
  "SKIP_2": {
    "title": "card.skip.title",
    "subtitle": "card.skip.subtitle2",
    "description": "card.skip.description",
    "imageUrl": "skip_2.png"
  },
  "SKIP_3": {
    "title": "card.skip.title",
    "subtitle": "card.skip.subtitle3",
    "description": "card.skip.description",
    "imageUrl": "skip_3.png"
  },
  "SEETHEFUTURE_1": {
    "title": "card.seeTheFuture.title",
    "subtitle": "card.seeTheFuture.subtitle1",
    "description": "card.seeTheFuture.description",
    "imageUrl": "see_the_future_1.png"
  },
  "SEETHEFUTURE_2": {
    "title": "card.seeTheFuture.title",
    "subtitle": "card.seeTheFuture.subtitle2",
    "description": "card.seeTheFuture.description",
    "imageUrl": "see_the_future_2.png"
  },
  "SEETHEFUTURE_3": {
    "title": "card.seeTheFuture.title",
    "subtitle": "card.seeTheFuture.subtitle3",
    "description": "card.seeTheFuture.description",
    "imageUrl": "see_the_future_3.png"
  },
  "SEETHEFUTURE_4": {
    "title": "card.seeTheFuture.title",
    "subtitle": "card.seeTheFuture.subtitle4",
    "description": "card.seeTheFuture.description",
    "imageUrl": "see_the_future_4.png"
  },
  "FERALCAT_1": {
    "title": "card.feralCat.title",
    "subtitle": "card.feralCat.subtitle1",
    "description": "card.feralCat.description",
    "imageUrl": "feralCat_1.png"
  },
  "FERALCAT_2": {
    "title": "card.feralCat.title",
    "subtitle": "card.feralCat.subtitle2",
    "description": "card.feralCat.description",
    "imageUrl": "feralCat_2.png"
  },
  "FERALCAT_3": {
    "title": "card.feralCat.title",
    "subtitle": "card.feralCat.subtitle3",
    "description": "card.feralCat.description",
    "imageUrl": "feralCat_3.png"
  },
  "FERALCAT_4": {
    "title": "card.feralCat.title",
    "subtitle": "card.feralCat.subtitle4",
    "description": "card.feralCat.description",
    "imageUrl": "feralCat_4.png"
  },
  "CATCARD_11": {
    "title": "card.catcard1.title",
    "subtitle": "global.empty",
    "description": "THIS IS A CAT CARD AND IS POWERLESS ON ITS OWN.",
    "imageUrl": "cat_card_1.png"
  },
  "CATCARD_12": {
    "title": "card.catcard1.title",
    "subtitle": "global.empty",
    "description": "card.catcard.description",
    "imageUrl": "cat_card_1.png"
  },
  "CATCARD_13": {
    "title": "card.catcard1.title",
    "subtitle": "global.empty",
    "description": "card.catcard.description",
    "imageUrl": "cat_card_1.png"
  },
  "CATCARD_14": {
    "title": "card.catcard1.title",
    "subtitle": "global.empty",
    "description": "card.catcard.description",
    "imageUrl": "cat_card_1.png"
  },
  "CATCARD_21": {
    "title": "card.catcard2.title",
    "subtitle": "global.empty",
    "description": "card.catcard.description",
    "imageUrl": "cat_card_2.png"
  },
  "CATCARD_22": {
    "title": "card.catcard2.title",
    "subtitle": "global.empty",
    "description": "card.catcard.description",
    "imageUrl": "cat_card_2.png"
  },
  "CATCARD_23": {
    "title": "card.catcard2.title",
    "subtitle": "global.empty",
    "description": "card.catcard.description",
    "imageUrl": "cat_card_2.png"
  },
  "CATCARD_24": {
    "title": "card.catcard2.title",
    "subtitle": "global.empty",
    "description": "card.catcard.description",
    "imageUrl": "cat_card_2.png"
  },
  "CATCARD_31": {
    "title": "card.catcard3.title",
    "subtitle": "global.empty",
    "description": "card.catcard.description",
    "imageUrl": "cat_card_3.png"
  },
  "CATCARD_32": {
    "title": "card.catcard3.title",
    "subtitle": "global.empty",
    "description": "card.catcard.description",
    "imageUrl": "cat_card_3.png"
  },
  "CATCARD_33": {
    "title": "card.catcard3.title",
    "subtitle": "global.empty",
    "description": "card.catcard.description",
    "imageUrl": "cat_card_3.png"
  },
  "CATCARD_34": {
    "title": "card.catcard3.title",
    "subtitle": "global.empty",
    "description": "card.catcard.description",
    "imageUrl": "cat_card_3.png"
  },
  "CATCARD_41": {
    "title": "card.catcard4.title",
    "subtitle": "global.empty",
    "description": "card.catcard.description",
    "imageUrl": "cat_card_4.png"
  },
  "CATCARD_42": {
    "title": "card.catcard4.title",
    "subtitle": "global.empty",
    "description": "card.catcard.description",
    "imageUrl": "cat_card_4.png"
  },
  "CATCARD_43": {
    "title": "card.catcard4.title",
    "subtitle": "global.empty",
    "description": "card.catcard.description",
    "imageUrl": "cat_card_4.png"
  },
  "CATCARD_44": {
    "title": "card.catcard4.title",
    "subtitle": "global.empty",
    "description": "card.catcard.description",
    "imageUrl": "cat_card_4.png"
  },
  "CATOMICBOMB_1": {
    "title": "card.catomicBomb.title",
    "subtitle": "card.catomicBomb.subtitle",
    "description": "card.catomicBomb.description",
    "imageUrl": "catomic_bomb.png"
  },
  "SUPERSKIP_1": {
    "title": "card.superSkip.title",
    "subtitle": "card.superSkip.subtitle1",
    "description": "card.superSkip.description",
    "imageUrl": "superSkip_1.png"
  },
  "SUPERSKIP_2": {
    "title": "card.superSkip.title",
    "subtitle": "card.superSkip.subtitle2",
    "description": "card.superSkip.description",
    "imageUrl": "superSkip_2.png"
  },
  "GODCAT_1": {
    "title": "card.godcat.title",
    "subtitle": "card.godcat.subtitle",
    "description": "card.godcat.description",
    "imageUrl": "godcat_1.png"
  },
  "CLONE_1": {
    "title": "card.clone.title",
    "subtitle": "card.clone.subtitle1",
    "description": "card.clone.description",
    "imageUrl": "clone_1.png"
  },
  "CLONE_2": {
    "title": "card.clone.title",
    "subtitle": "card.clone.subtitle2",
    "description": "card.clone.description",
    "imageUrl": "clone_2.png"
  },
  "CLONE_3": {
    "title": "card.clone.title",
    "subtitle": "card.clone.subtitle3",
    "description": "card.clone.description",
    "imageUrl": "clone_3.png"
  },
  "SWAPTOPANDBOTTOM_1": {
    "title": "card.swapTopAndBottom.title",
    "subtitle": "card.swapTopAndBottom.subtitle1",
    "description": "card.swapTopAndBottom.description",
    "imageUrl": "swap_top_and_bottom_1.png"
  },
  "SWAPTOPANDBOTTOM_2": {
    "title": "card.swapTopAndBottom.title",
    "subtitle": "card.swapTopAndBottom.subtitle2",
    "description": "card.swapTopAndBottom.description",
    "imageUrl": "swap_top_and_bottom_2.png"
  },
  "SWAPTOPANDBOTTOM_3": {
    "title": "card.swapTopAndBottom.title",
    "subtitle": "card.swapTopAndBottom.subtitle3",
    "description": "card.swapTopAndBottom.description",
    "imageUrl": "swap_top_and_bottom_3.png"
  },
  "DRAWFROMTHEBOTTOM_1": {
    "title": "card.drawFromTheBottom.title",
    "subtitle": "card.drawFromTheBottom.subtitle1",
    "description": "card.drawFromTheBottom.description",
    "imageUrl": "draw_from_the_bottom_1.png"
  },
  "DRAWFROMTHEBOTTOM_2": {
    "title": "card.drawFromTheBottom.title",
    "subtitle": "card.drawFromTheBottom.subtitle2",
    "description": "card.drawFromTheBottom.description",
    "imageUrl": "draw_from_the_bottom_2.png"
  },
  "DRAWFROMTHEBOTTOM_3": {
    "title": "card.drawFromTheBottom.title",
    "subtitle": "card.drawFromTheBottom.subtitle3",
    "description": "card.drawFromTheBottom.description",
    "imageUrl": "draw_from_the_bottom_3.png"
  },
  "TARGETEDATTACK_1": {
    "title": "card.targetedAttack.title",
    "subtitle": "card.targetedAttack.subtitle1",
    "description": "card.targetedAttack.description",
    "imageUrl": "targeted_attack_1.png"
  },
  "TARGETEDATTACK_2": {
    "title": "card.targetedAttack.title",
    "subtitle": "card.targetedAttack.subtitle2",
    "description": "card.targetedAttack.description",
    "imageUrl": "targeted_attack_2.png"
  },
  "TARGETEDATTACK_3": {
    "title": "card.targetedAttack.title",
    "subtitle": "card.targetedAttack.subtitle3",
    "description": "card.targetedAttack.description",
    "imageUrl": "targeted_attack_3.png"
  },
  "TARGETEDATTACK_4": {
    "title": "card.targetedAttack.title",
    "subtitle": "card.targetedAttack.subtitle4",
    "description": "card.targetedAttack.description",
    "imageUrl": "targeted_attack_4.png"
  },
  "WINNERWINNERCATNIPDINNER_1": {
    "title": "card.winnerWinnerCatnipDinner.title",
    "subtitle": "card.winnerWinnerCatnipDinner.subtitle",
    "description": "card.winnerWinnerCatnipDinner.description",
    "imageUrl": "winner_winner_catnip_dinner_1.png"
  },
  "RAGEBAIT_1": {
    "title": "card.ragebait.title",
    "subtitle": "card.ragebait.subtitle",
    "description": "card.ragebait.description",
    "imageUrl": "ragebait_1.png"
  },
  "RECYCLE_1": {
    "title": "card.recycle.title",
    "subtitle": "card.recycle.subtitle",
    "description": "card.recycle.description",
    "imageUrl": "recycle_1.png"
  },
  "DOUBLEUP_1": {
    "title": "card.doubleUp.title",
    "subtitle": "card.doubleUp.subtitle",
    "description": "card.doubleUp.description",
    "imageUrl": "double_up_1.png"
  },
  "MILDDRAW_1": {
    "title": "card.mildDraw.title",
    "subtitle": "card.mildDraw.subtitle",
    "description": "card.mildDraw.description",
    "imageUrl": "mildDraw_1.png"
  }
}